Workbook

Sheet Balance des comptes
A2: MCI CARE MADAGASCAR | I2: Balance des comptes | O2: Période du | P2: 46023
O3: au | P3: 46387
I4: Complète | O4: Tenue de compte : MGA
A6: © Sage - Sage 100cloud Comptabilité Standard 6.01 | I6: Date de tirage | K6: 46295 | M6: à | N6: 0.49244213 | P6: Page : | R6: 1
A8: Numéro de compte | J8: Mouvements | P8: Soldes
E9: Intitulé des comptes
J10: Débit | L10: Crédit | O10: Débit | Q10: Crédit
A13: 101000 | C13: Capital social | M13: 1000000 | R13: 1000000
A14: 110000 | C14: Report à nouveau (créditeur) | M14: 3.6357538e+08 | R14: 3.6357538e+08
A15: 120000 | C15: Résultat exercice (bénéfice) | J15: 2.0190225e+08 | M15: 1.4335208e+09 | R15: 1.2316186e+09
A16: 129000 | C16: Résultat exercice (perte) | J16: 27022531 | O16: 27022531
A17: 204000 | C17: Logiciels informatiques et assimilé | J17: 63305140 | O17: 63305140
A18: 212000 | C18: Mobilier de bureau | J18: 11611131 | O18: 11611131
A19: 215000 | C19: Installation technique | J19: 230000 | O19: 230000
A20: 216000 | C20: Matériel Outillage | J20: 290000 | O20: 290000
A21: 218200 | C21: Matériel informatique | J21: 2.5723672e+08 | O21: 2.5723672e+08
A22: 238000 | C22: Immobilisation incorporelle en cour | J22: 12536740 | O22: 12536740
A23: 275000 | C23: Dépots et cautionnements verés-CHU | J23: 800000 | O23: 800000
A24: 280400 | C24: Amortissement logiciel | M24: 62906140 | R24: 62906140
A25: 281200 | C25: Amortissement mobilier de bureau | M25: 8261092.3 | R25: 8261092.3
A26: 281500 | C26: Amortissement installation techniqu | M26: 230000 | R26: 230000
A27: 281600 | C27: Amortissement matériel et outillage | M27: 290000 | R27: 290000
A28: 281820 | C28: Amortissement matériel informatique | M28: 1.7915165e+08 | R28: 1.7915165e+08
A29: 401000 | C29: Prestataire | J29: 7.7207628e+09 | M29: 7.7187505e+09 | O29: 2012346
A30: 401100 | C30: Fournisseur MCI Care | J30: 4.7984224e+08 | M30: 4.9926144e+08 | R30: 19419197
A31: 408000 | C31: facture non parvenue | J31: 22987486 | M31: 22987486
A32: 409300 | C32: avances fournisseur local | J32: 72000 | M32: 72000
A33: 411100 | C33: SANLAM | J33: 2.7186415e+08 | M33: 2.7186415e+08 | R33: 0.019999981
A34: 411102 | C34: EXSANLAMALLIANZ | J34: 38525178 | M34: 38525178
A35: 411103 | C35: SANLAMALLIANZ | J35: 7.2894338e+08 | M35: 6.2136827e+08 | O35: 1.0757511e+08
A36: 411110 | C36: HOLCIM/CEMENTIS | J36: 68830658 | M36: 61469636 | O36: 7361022
A37: 411121 | C37: DHL EXPRESS | J37: 8184360.2 | M37: 8184360.2
A38: 411122 | C38: DHL FORWARDING | J38: 10738898 | M38: 8463454.9 | O38: 2275443.1
A39: 411123 | C39: MGS | J39: 943987.2 | O39: 943987.2
A40: 411124 | C40: FSS | J40: 8415340.3 | M40: 4661536.5 | O40: 3753803.8
A41: 411130 | C41: PAMF | J41: 77571040 | M41: 77571040
A42: 411140 | C42: TELMA | J42: 45700000 | M42: 45700000
A43: 411145 | C43: TELMA MONEY | J43: 15988672 | M43: 15988672
A44: 411150 | C44: JOVENA | J44: 15886567 | M44: 15886567
A45: 411160 | C45: ERNST & YOUNG | J45: 10284505 | M45: 10284505
A46: 411171 | C46: INTELCIA MADAGASCAR | J46: 4200000 | M46: 3780000 | O46: 420000
A47: 411180 | C47: MCB | J47: 20826687 | M47: 19708551 | O47: 1118135.4
A48: 411190 | C48: EASY TECH | J48: 6548480.3 | M48: 6548480.3
A49: 411201 | C49: GROUPE TALYS | J49: 15122759 | M49: 14334024 | O49: 788734.56
A50: 411202 | C50: TALYS HOSPITALISATION | J50: 1461434 | M50: 1419266 | O50: 42168
A51: 411204 | C51: TALYS STMB | J51: 960012.75 | M51: 863087.75 | O51: 96925
A52: 411205 | C52: TALYS STMB HOSP | J52: 46771.2 | M52: 46771.2
A53: 411206 | C53: TALYS TAMBOHO | J53: 3344020.5 | M53: 3187890.9 | O53: 156129.6
A54: 411207 | C54: TALYS TAMBOHO HOSP | J54: 219611.74 | M54: 219611.74
A55: 411210 | C55: AITS | J55: 4253015.4 | M55: 4253015.4
A56: 411211 | C56: STELLARIX | J56: 1122018 | M56: 1122018
A57: 411220 | C57: AXIANSS | J57: 5853431 | M57: 5853431
A58: 411222 | C58: ATSS | J58: 8493067.3 | M58: 8493067.3
A59: 411223 | C59: VIA ASSURANCE | J59: 576000 | M59: 576000
A60: 411230 | C60: CONNECTEO | J60: 8017752.7 | M60: 8017752.7
A61: 411240 | C61: TOM | J61: 4921765.4 | M61: 4921765.4
A62: 411250 | C62: EDM/NEA | J62: 11571118 | M62: 11571118
A63: 411260 | C63: GROUPE FIRST IMMO | J63: 17012571 | M63: 17101401 | R63: 88830
A64: 411262 | C64: SANKO | J64: 887857.91 | M64: 887857.91
A65: 411270 | C65: WELIGHT | J65: 2091724 | M65: 2091724
A66: 411271 | C66: AXIAN UNIVERSITY | J66: 806742.84 | M66: 806742.84
A67: 411272 | C67: FONDATION AXIAN | J67: 469476 | M67: 469476
A68: 411320 | C68: BOOST | J68: 13452609 | M68: 11611689 | O68: 1840920.7
A69: 411321 | C69: JBU | J69: 11867740 | M69: 10085090 | O69: 1782650.6
A70: 411322 | C70: JBS | J70: 10802111 | M70: 8410331.3 | O70: 2391780
A71: 411330 | C71: LECOFRUIT | J71: 8764478.5 | M71: 8231880.1 | O71: 532598.4
A72: 411332 | C72: TANJAKA FOOD | J72: 31584 | M72: 30144 | O72: 1440
A73: 411340 | C73: OIM | J73: 280099.2 | M73: 262646.4 | O73: 17452.8
A74: 411350 | C74: OMNIVEST | J74: 1677638.4 | M74: 1400064 | O74: 277574.4
A75: 411360 | C75: OIM-EXPORT | J75: 10155610 | M75: 9598794.4 | O75: 556815.36
A76: 411370 | C76: Cl. SOCOLAIT | J76: 6143891.3 | M76: 5536931.3 | O76: 606960
A77: 411400 | C77: MADCOM | J77: 11901168 | M77: 11390937 | O77: 510230.88
A78: 411601 | C78: EVIOSYS | J78: 9900000 | M78: 8910000 | O78: 990000
A79: 411602 | C79: INGEDATA | J79: 2932459.6 | M79: 2932459.6
A80: 411603 | C80: CAMUSAT | J80: 12000000 | M80: 12000000
A81: 411700 | C81: SMARTONE | J81: 12167033 | M81: 12167033
A82: 411710 | C82: FOUNDEVER | J82: 1737821.3 | O82: 1737821.3
A83: 411800 | C83: Cl. NACRE SOLUTIONS | J83: 11470170 | M83: 10870170 | O83: 600000
A84: 411801 | C84: Cl. NACRE DIRECTIONS | J84: 600000 | M84: 600000
A85: 411802 | C85: RAHARIVOLA BRUNO | J85: 2011822.5 | M85: 2011822.5
A86: 411900 | C86: Cl. STAR | J86: 2.4319699e+08 | M86: 2.4319699e+08
A87: 411910 | C87: TALOUMIS | J87: 64514505 | M87: 29916091 | O87: 34598414
A88: 411921 | C88: MADAGASCO | J88: 3514594.2 | M88: 3412594.2 | O88: 102000
A89: 418000 | C89: Facture à établir | J89: 2.0688631e+08 | M89: 2.0688631e+08
A90: 421000 | C90: Personnel, Rémunération dûe | J90: 3.2576092e+08 | M90: 3.2577092e+08 | R90: 10000
A91: 425000 | C91: Avances au personnel mensuel | J91: 8350000 | M91: 7700000 | O91: 650000
A92: 428100 | C92: Personnel, Congés à payer | J92: 81983238 | M92: 1.540082e+08 | R92: 72024963
A93: 431100 | C93: CNAPS | J93: 40813773 | M93: 49173462 | R93: 8359689.5
A94: 431101 | C94: CNAPS, Allocation familiale | J94: 1192000 | M94: 1192000
A95: 431200 | C95: ESIA | J95: 17491617 | M95: 21074341 | R95: 3582724.1
A96: 431300 | C96: FMFP | J96: 2915269 | M96: 4574389.7 | R96: 1659120.7
A97: 433000 | C97: Organisme retraite, SAHAM | J97: 3260509.1 | M97: 4785709.1 | R97: 1525200
A98: 444100 | C98: Etat, IR | M98: 64839964 | R98: 64839964
A99: 444200 | C99: Etat, Acompte sur IR | J99: 1.520492e+08 | O99: 1.520492e+08
A100: 444400 | C100: Etat, IRI Fournisseur LOCAL | J100: 575965.73 | M100: 575965.73
A101: 444410 | C101: Etat, IRI Fournisseur ETRANGER | J101: 1992415 | M101: 6475603.5 | R101: 4483188.5
A102: 445500 | C102: Etat, TVA à payer | J102: 1.2491227e+08 | M102: 1.2986266e+08 | R102: 4950391.8
A103: 445600 | C103: Etat, TVA déductible sur biens et s | J103: 69830302 | M103: 61099606 | O103: 8730695.7
A104: 445610 | C104: Etat, TVA déductible Intermittent | J104: 3822603.5 | M104: 3822603.5
A105: 445640 | C105: Etat, TVA déductible sur Immo | J105: 1546600 | M105: 1546600
...

Sheet 2026
A1: HOLCIM | C1: DEBIT | D1: CREDIT | E1: SOLDE
B2: 467110 | C2: =IFERROR(INDEX('Balance des comptes'!$O:$O,MATCH('2026'!B2,'Balance des comptes'!$A:$A,0)),0) -> 0 | D2: =IFERROR(INDEX('Balance des comptes'!$R:$R,MATCH('2026'!B2,'Balance des comptes'!$A:$A,0)),0) -> 32571587 | E2: =+C2-D2 -> -32571587
B3: 460110 | C3: =IFERROR(INDEX('Balance des comptes'!$O:$O,MATCH('2026'!B3,'Balance des comptes'!$A:$A,0)),0) -> 30278601 | D3: =IFERROR(INDEX('Balance des comptes'!$R:$R,MATCH('2026'!B3,'Balance des comptes'!$A:$A,0)),0) -> 0 | E3: =+C3-D3 -> 30278601
B4: 461110 | C4: =IFERROR(INDEX('Balance des comptes'!$O:$O,MATCH('2026'!B4,'Balance des comptes'!$A:$A,0)),0) -> 0 | D4: =IFERROR(INDEX('Balance des comptes'!$R:$R,MATCH('2026'!B4,'Balance des comptes'!$A:$A,0)),0) -> 0 | E4: =+C4-D4 -> 0
B5: 462110 | C5: =IFERROR(INDEX('Balance des comptes'!$O:$O,MATCH('2026'!B5,'Balance des comptes'!$A:$A,0)),0) -> 0 | D5: =IFERROR(INDEX('Balance des comptes'!$R:$R,MATCH('2026'!B5,'Balance des comptes'!$A:$A,0)),0) -> 170100 | E5: =+C5-D5 -> -170100
B6: Solde Appel de fonds | C6: =SUM(C2:C5) -> 30278601 | D6: =SUM(D2:D5) -> 32741687 | E6: =SUM(E2:E5) -> -2463085.9
B7: 512110 | C7: =IFERROR(INDEX('Balance des comptes'!$O:$O,MATCH('2026'!B7,'Balance des comptes'!$A:$A,0)),0) -> 1489728.7 | D7: =IFERROR(INDEX('Balance des comptes'!$R:$R,MATCH('2026'!B7,'Balance des comptes'!$A:$A,0)),0) -> 0 | E7: =+C7-D7 -> 1489728.7
B8: Solde Trésorerie | C8: =SUM(C7:C7) -> 1489728.7 | D8: =SUM(D7:D7) -> 0 | E8: =SUM(E7:E7) -> 1489728.7
B10: Vérification | E10: =+E6+E8 -> -973357.22
A12: DHL INTERNATIONAL | C12: DEBIT | D12: CREDIT | E12: SOLDE
B13: 467120 | C13: =IFERROR(INDEX('Balance des comptes'!$O:$O,MATCH('2026'!B13,'Balance des comptes'!$A:$A,0)),0) -> 0 | D13: =IFERROR(INDEX('Balance des comptes'!$R:$R,MATCH('2026'!B13,'Balance des comptes'!$A:$A,0)),0) -> 1.4047267e+08 | E13: =+C13-D13 -> -1.4047267e+08
B14: 460120 | C14: =IFERROR(INDEX('Balance des comptes'!$O:$O,MATCH('2026'!B14,'Balance des comptes'!$A:$A,0)),0) -> 0 | D14: =IFERROR(INDEX('Balance des comptes'!$R:$R,MATCH('2026'!B14,'Balance des comptes'!$A:$A,0)),0) -> 0 | E14: =+C14-D14 -> 0
B15: 461120 | C15: =IFERROR(INDEX('Balance des comptes'!$O:$O,MATCH('2026'!B15,'Balance des comptes'!$A:$A,0)),0) -> 0 | D15: =IFERROR(INDEX('Balance des comptes'!$R:$R,MATCH('2026'!B15,'Balance des comptes'!$A:$A,0)),0) -> 0 | E15: =+C15-D15 -> 0
B16: 462120 | C16: =IFERROR(INDEX('Balance des comptes'!$O:$O,MATCH('2026'!B16,'Balance des comptes'!$A:$A,0)),0) -> 0 | D16: =IFERROR(INDEX('Balance des comptes'!$R:$R,MATCH('2026'!B16,'Balance des comptes'!$A:$A,0)),0) -> 0 | E16: =+C16-D16 -> 0
B17: Solde Appel de fonds | C17: =SUM(C13:C16) -> 0 | D17: =SUM(D13:D16) -> 1.4047267e+08 | E17: =SUM(E13:E16) -> -1.4047267e+08
B18: 512120 | C18: =IFERROR(INDEX('Balance des comptes'!$O:$O,MATCH('2026'!B18,'Balance des comptes'!$A:$A,0)),0) -> 0 | D18: =IFERROR(INDEX('Balance des comptes'!$R:$R,MATCH('2026'!B18,'Balance des comptes'!$A:$A,0)),0) -> 69969.22 | E18: =+C18-D18 -> -69969.22 | G18: Solde Appel de fonds | H18: =+E17+E28 -> 69969.02
B19: Solde Trésorerie | C19: =SUM(C18:C18) -> 0 | D19: =SUM(D18:D18) -> 69969.22 | E19: =SUM(E18:E18)-E15 -> -69969.22 | G19: Solde Trésorerie | H19: =+E19 -> -69969.22
G20: Vérification | H20: =+H18+H19 -> -0.20000002
B21: Vérification | E21: =+E17+E19 -> -1.4054264e+08
A23: DHL EXPRESS | C23: DEBIT | D23: CREDIT | E23: SOLDE
B24: 467121 | C24: =IFERROR(INDEX('Balance des comptes'!$O:$O,MATCH('2026'!B24,'Balance des comptes'!$A:$A,0)),0) -> 1.4430838e+08 | D24: =IFERROR(INDEX('Balance des comptes'!$R:$R,MATCH('2026'!B24,'Balance des comptes'!$A:$A,0)),0) -> 0 | E24: =+C24-D24 -> 1.4430838e+08
B25: 460121 | C25: =IFERROR(INDEX('Balance des comptes'!$O:$O,MATCH('2026'!B25,'Balance des comptes'!$A:$A,0)),0) -> 0 | D25: =IFERROR(INDEX('Balance des comptes'!$R:$R,MATCH('2026'!B25,'Balance des comptes'!$A:$A,0)),0) -> 0 | E25: =+C25-D25 -> 0
B26: 461121 | C26: =IFERROR(INDEX('Balance des comptes'!$O:$O,MATCH('2026'!B26,'Balance des comptes'!$A:$A,0)),0) -> 0 | D26: =IFERROR(INDEX('Balance des comptes'!$R:$R,MATCH('2026'!B26,'Balance des comptes'!$A:$A,0)),0) -> 0 | E26: =+C26-D26 -> 0
B27: 462121 | C27: =IFERROR(INDEX('Balance des comptes'!$O:$O,MATCH('2026'!B27,'Balance des comptes'!$A:$A,0)),0) -> 0 | D27: =IFERROR(INDEX('Balance des comptes'!$R:$R,MATCH('2026'!B27,'Balance des comptes'!$A:$A,0)),0) -> 3765734 | E27: =+C27-D27 -> -3765734
B28: Solde Appel de fonds | C28: =SUM(C24:C27) -> 1.4430838e+08 | D28: =SUM(D24:D27) -> 3765734 | E28: =SUM(E24:E27) -> 1.4054264e+08
A31: MGS | C31: DEBIT | D31: CREDIT | E31: SOLDE
B32: 467123 | C32: =IFERROR(INDEX('Balance des comptes'!$O:$O,MATCH('2026'!B32,'Balance des comptes'!$A:$A,0)),0) -> 0 | D32: =IFERROR(INDEX('Balance des comptes'!$R:$R,MATCH('2026'!B32,'Balance des comptes'!$A:$A,0)),0) -> 5416187.9 | E32: =+C32-D32 -> -5416187.9
B33: 460123 | C33: =IFERROR(INDEX('Balance des comptes'!$O:$O,MATCH('2026'!B33,'Balance des comptes'!$A:$A,0)),0) -> 0 | D33: =IFERROR(INDEX('Balance des comptes'!$R:$R,MATCH('2026'!B33,'Balance des comptes'!$A:$A,0)),0) -> 0 | E33: =+C33-D33 -> 0 | G33: Solde Appel de fonds | H33: =+E36+E43 -> -8624968.8
B34: 461123 | C34: =IFERROR(INDEX('Balance des comptes'!$O:$O,MATCH('2026'!B34,'Balance des comptes'!$A:$A,0)),0) -> 0 | D34: =IFERROR(INDEX('Balance des comptes'!$R:$R,MATCH('2026'!B34,'Balance des comptes'!$A:$A,0)),0) -> 0 | E34: =+C34-D34 -> 0 | G34: Solde Trésorerie | H34: =+E45 -> 8795039.8
B35: 462123 | C35: =IFERROR(INDEX('Balance des comptes'!$O:$O,MATCH('2026'!B35,'Balance des comptes'!$A:$A,0)),0) -> 0 | D35: =IFERROR(INDEX('Balance des comptes'!$R:$R,MATCH('2026'!B35,'Balance des comptes'!$A:$A,0)),0) -> 201300 | E35: =+C35-D35 -> -201300 | G35: Vérification | H35: =+H33+H34 -> 170071
B36: Solde Appel de fonds | C36: =SUM(C32:C35) -> 0 | D36: =SUM(D32:D35) -> 5617487.9 | E36: =SUM(E32:E35) -> -5617487.9
A38: FSS | C38: DEBIT | D38: CREDIT | E38: SOLDE
B39: 467124 | C39: =IFERROR(INDEX('Balance des comptes'!$O:$O,MATCH('2026'!B39,'Balance des comptes'!$A:$A,0)),0) -> 0 | D39: =IFERROR(INDEX('Balance des comptes'!$R:$R,MATCH('2026'!B39,'Balance des comptes'!$A:$A,0)),0) -> 20288474 | E39: =+C39-D39 -> -20288474
B40: 460124 | C40: =IFERROR(INDEX('Balance des comptes'!$O:$O,MATCH('2026'!B40,'Balance des comptes'!$A:$A,0)),0) -> 17280994 | D40: =IFERROR(INDEX('Balance des comptes'!$R:$R,MATCH('2026'!B40,'Balance des comptes'!$A:$A,0)),0) -> 0 | E40: =+C40-D40 -> 17280994
B41: 461124 | C41: =IFERROR(INDEX('Balance des comptes'!$O:$O,MATCH('2026'!B41,'Balance des comptes'!$A:$A,0)),0) -> 0 | D41: =IFERROR(INDEX('Balance des comptes'!$R:$R,MATCH('2026'!B41,'Balance des comptes'!$A:$A,0)),0) -> 0 | E41: =+C41-D41 -> 0
B42: 462124 | C42: =IFERROR(INDEX('Balance des comptes'!$O:$O,MATCH('2026'!B42,'Balance des comptes'!$A:$A,0)),0) -> 0 | D42: =IFERROR(INDEX('Balance des comptes'!$R:$R,MATCH('2026'!B42,'Balance des comptes'!$A:$A,0)),0) -> 0 | E42: =+C42-D42 -> 0
B43: Solde Appel de fonds | C43: =SUM(C39:C42) -> 17280994 | D43: =SUM(D39:D42) -> 20288474 | E43: =SUM(E39:E42) -> -3007480.9
B44: 512124 | C44: =IFERROR(INDEX('Balance des comptes'!$O:$O,MATCH('2026'!B44,'Balance des comptes'!$A:$A,0)),0) -> 8795039.8 | D44: =IFERROR(INDEX('Balance des comptes'!$R:$R,MATCH('2026'!B44,'Balance des comptes'!$A:$A,0)),0) -> 0 | E44: =+C44-D44 -> 8795039.8
B45: Solde Trésorerie | C45: =SUM(C44:C44) -> 8795039.8 | D45: =SUM(D44:D44) -> 0 | E45: =SUM(E44:E44) -> 8795039.8
B47: Vérification | E47: =+E43+E45+E36 -> 170071
A49: DHL GLOBAL FORWARDING | C49: DEBIT | D49: CREDIT | E49: SOLDE
B50: 467122 | C50: =IFERROR(INDEX('Balance des comptes'!$O:$O,MATCH('2026'!B50,'Balance des comptes'!$A:$A,0)),0) -> 0 | D50: =IFERROR(INDEX('Balance des comptes'!$R:$R,MATCH('2026'!B50,'Balance des comptes'!$A:$A,0)),0) -> 26421345 | E50: =+C50-D50 -> -26421345
B51: 460122 | C51: =IFERROR(INDEX('Balance des comptes'!$O:$O,MATCH('2026'!B51,'Balance des comptes'!$A:$A,0)),0) -> 0 | D51: =IFERROR(INDEX('Balance des comptes'!$R:$R,MATCH('2026'!B51,'Balance des comptes'!$A:$A,0)),0) -> 0 | E51: =+C51-D51 -> 0
B52: 461122 | C52: =IFERROR(INDEX('Balance des comptes'!$O:$O,MATCH('2026'!B52,'Balance des comptes'!$A:$A,0)),0) -> 0 | D52: =IFERROR(INDEX('Balance des comptes'!$R:$R,MATCH('2026'!B52,'Balance des comptes'!$A:$A,0)),0) -> 0
B53: 462122 | C53: =IFERROR(INDEX('Balance des comptes'!$O:$O,MATCH('2026'!B53,'Balance des comptes'!$A:$A,0)),0) -> 0 | D53: =IFERROR(INDEX('Balance des comptes'!$R:$R,MATCH('2026'!B53,'Balance des comptes'!$A:$A,0)),0) -> 0
B54: Solde Appel de fonds | C54: =SUM(C50:C53) -> 0 | D54: =SUM(D50:D53) -> 26421345 | E54: =SUM(E50:E53) -> -26421345
B55: 512122 | C55: =IFERROR(INDEX('Balance des comptes'!$O:$O,MATCH('2026'!B55,'Balance des comptes'!$A:$A,0)),0) -> 19291335 | D55: =IFERROR(INDEX('Balance des comptes'!$R:$R,MATCH('2026'!B55,'Balance des comptes'!$A:$A,0)),0) -> 0 | E55: =+C55-D55 -> 19291335
B56: Solde Trésorerie | C56: =SUM(C55:C55) -> 19291335 | D56: =SUM(D55:D55) -> 0 | E56: =SUM(E55:E55)-E52 -> 19291335
B58: Vérification | E58: =+E54+E56 -> -7130009.4
A63: DHL PRONET | C63: DEBIT | D63: CREDIT | E63: SOLDE
B64: 467124 | C64: =+IFERROR(VLOOKUP($B64,#REF!,6,0),0) -> 0 | D64: =IFERROR(VLOOKUP($B64,#REF!,7,0),0) -> 0 | E64: =+C64-D64 -> 0
B65: 460124 | C65: =+IFERROR(VLOOKUP($B65,#REF!,6,0),0) -> 0 | D65: =IFERROR(VLOOKUP($B65,#REF!,7,0),0) -> 0 | E65: =+C65-D65 -> 0
B66: 461124 | C66: =+IFERROR(VLOOKUP($B66,#REF!,6,0),0) -> 0 | D66: =IFERROR(VLOOKUP($B66,#REF!,7,0),0) -> 0 | E66: =+C66-D66 -> 0
B67: 462124 | C67: =+IFERROR(VLOOKUP($B67,#REF!,6,0),0) -> 0 | D67: =IFERROR(VLOOKUP($B67,#REF!,7,0),0) -> 0 | E67: =+C67-D67 -> 0
B68: Solde Appel de fonds | C68: =SUM(C64:C67) -> 0 | D68: =SUM(D64:D67) -> 0 | E68: =SUM(E64:E67) -> 0
B69: 512124 | C69: =+IFERROR(VLOOKUP($B69,#REF!,6,0),0) -> 0 | D69: =IFERROR(VLOOKUP($B69,#REF!,7,0),0) -> 0 | E69: =SUM(C69:D69) -> 0
B70: 513124 | C70: =+IFERROR(VLOOKUP($B70,#REF!,6,0),0) -> 0 | D70: =IFERROR(VLOOKUP($B70,#REF!,7,0),0) -> 0 | E70: =SUM(C70:D70) -> 0
B71: Solde Trésorerie | C71: =SUM(C69:C70) -> 0 | D71: =SUM(D69:D70) -> 0 | E71: =SUM(E69:E70)-E66 -> 0
B73: Vérification | E73: =+E68-E71 -> 0
A76: TELMA SA | C76: DEBIT | D76: CREDIT | E76: SOLDE
B77: 467140 | C77: =IFERROR(INDEX('Balance des comptes'!$O:$O,MATCH('2026'!B77,'Balance des comptes'!$A:$A,0)),0) -> 0 | D77: =IFERROR(INDEX('Balance des comptes'!$R:$R,MATCH('2026'!B77,'Balance des comptes'!$A:$A,0)),0) -> 91439426 | E77: =+C77-D77 -> -91439426
B78: 460140 | C78: =IFERROR(INDEX('Balance des comptes'!$O:$O,MATCH('2026'!B78,'Balance des comptes'!$A:$A,0)),0) -> 91062101 | D78: =IFERROR(INDEX('Balance des comptes'!$R:$R,MATCH('2026'!B78,'Balance des comptes'!$A:$A,0)),0) -> 0 | E78: =+C78-D78 -> 91062101
B79: 461140 | C79: =IFERROR(INDEX('Balance des comptes'!$O:$O,MATCH('2026'!B79,'Balance des comptes'!$A:$A,0)),0) -> 0 | D79: =IFERROR(INDEX('Balance des comptes'!$R:$R,MATCH('2026'!B79,'Balance des comptes'!$A:$A,0)),0) -> 0 | E79: =+C79-D79 -> 0
B80: 462140 | C80: =IFERROR(INDEX('Balance des comptes'!$O:$O,MATCH('2026'!B80,'Balance des comptes'!$A:$A,0)),0) -> 0 | D80: =IFERROR(INDEX('Balance des comptes'!$R:$R,MATCH('2026'!B80,'Balance des comptes'!$A:$A,0)),0) -> 5788333 | E80: =+C80-D80 -> -5788333
B81: Solde Appel de fonds | C81: =SUM(C77:C80) -> 91062101 | D81: =SUM(D77:D80) -> 97227759 | E81: =SUM(E77:E80) -> -6165658.4 | G81: Solde Appel de fonds | H81: =E81+E91 -> -5760692.3
B82: 512140 | C82: =IFERROR(INDEX('Balance des comptes'!$O:$O,MATCH('2026'!B82,'Balance des comptes'!$A:$A,0)),0) -> 4283967.3 | D82: =IFERROR(INDEX('Balance des comptes'!$R:$R,MATCH('2026'!B82,'Balance des comptes'!$A:$A,0)),0) -> 0 | E82: =+C82-D82 -> 4283967.3 | G82: Solde Trésorerie | H82: =E84 -> 7483876.3
B83: 513140 | C83: =IFERROR(INDEX('Balance des comptes'!$O:$O,MATCH('2026'!B83,'Balance des comptes'!$A:$A,0)),0) -> 3199909 | D83: =IFERROR(INDEX('Balance des comptes'!$R:$R,MATCH('2026'!B83,'Balance des comptes'!$A:$A,0)),0) -> 0 | E83: =+C83-D83 -> 3199909 | G83: Vérification | H83: =SUM(H81:H82) -> 1723184
B84: Solde Trésorerie | C84: =SUM(C82:C83) -> 7483876.3 | D84: =SUM(D82:D83) -> 0 | E84: =SUM(E82:E83) -> 7483876.3
A86: EVASAN | C86: DEBIT | D86: CREDIT | E86: SOLDE
B87: 467142 | C87: =IFERROR(INDEX('Balance des comptes'!$O:$O,MATCH('2026'!B87,'Balance des comptes'!$A:$A,0)),0) -> 404966.12 | D87: =IFERROR(INDEX('Balance des comptes'!$R:$R,MATCH('2026'!B87,'Balance des comptes'!$A:$A,0)),0) -> 0 | E87: =+C87-D87 -> 404966.12
B88: 460142 | C88: =IFERROR(INDEX('Balance des comptes'!$O:$O,MATCH('2026'!B88,'Balance des comptes'!$A:$A,0)),0) -> 0 | D88: =IFERROR(INDEX('Balance des comptes'!$R:$R,MATCH('2026'!B88,'Balance des comptes'!$A:$A,0)),0) -> 0 | E88: =+C88-D88 -> 0
B89: 461142 | C89: =IFERROR(INDEX('Balance des comptes'!$O:$O,MATCH('2026'!B89,'Balance des comptes'!$A:$A,0)),0) -> 0 | D89: =IFERROR(INDEX('Balance des comptes'!$R:$R,MATCH('2026'!B89,'Balance des comptes'!$A:$A,0)),0) -> 0 | E89: =+C89-D89 -> 0
B90: 462142 | C90: =IFERROR(INDEX('Balance des comptes'!$O:$O,MATCH('2026'!B90,'Balance des comptes'!$A:$A,0)),0) -> 0 | D90: =IFERROR(INDEX('Balance des comptes'!$R:$R,MATCH('2026'!B90,'Balance des comptes'!$A:$A,0)),0) -> 0 | E90: =+C90-D90 -> 0
B91: Solde Appel de fonds | C91: =SUM(C87:C90) -> 404966.12 | D91: =SUM(D87:D90) -> 0 | E91: =SUM(E87:E90) -> 404966.12
A95: TELMA MONEY | C95: DEBIT | D95: CREDIT | E95: SOLDE
B96: 467145 | C96: =IFERROR(INDEX('Balance des comptes'!$O:$O,MATCH('2026'!B96,'Balance des comptes'!$A:$A,0)),0) -> 0 | D96: =IFERROR(INDEX('Balance des comptes'!$R:$R,MATCH('2026'!B96,'Balance des comptes'!$A:$A,0)),0) -> 20259992 | E96: =+C96-D96 -> -20259992
B97: 460145 | C97: =IFERROR(INDEX('Balance des comptes'!$O:$O,MATCH('2026'!B97,'Balance des comptes'!$A:$A,0)),0) -> 12479060 | D97: =IFERROR(INDEX('Balance des comptes'!$R:$R,MATCH('2026'!B97,'Balance des comptes'!$A:$A,0)),0) -> 0 | E97: =+C97-D97 -> 12479060
B98: 461145 | C98: =IFERROR(INDEX('Balance des comptes'!$O:$O,MATCH('2026'!B98,'Balance des comptes'!$A:$A,0)),0) -> 0 | D98: =IFERROR(INDEX('Balance des comptes'!$R:$R,MATCH('2026'!B98,'Balance des comptes'!$A:$A,0)),0) -> 0 | E98: =+C98-D98 -> 0
B99: 462145 | C99: =IFERROR(INDEX('Balance des comptes'!$O:$O,MATCH('2026'!B99,'Balance des comptes'!$A:$A,0)),0) -> 0 | D99: =IFERROR(INDEX('Balance des comptes'!$R:$R,MATCH('2026'!B99,'Balance des comptes'!$A:$A,0)),0) -> 23797 | E99: =+C99-D99 -> -23797
B100: Solde Appel de fonds | C100: =SUM(C96:C99) -> 12479060 | D100: =SUM(D96:D99) -> 20283789 | E100: =SUM(E96:E99) -> -7804729.3
B101: 512145 | C101: =IFERROR(INDEX('Balance des comptes'!$O:$O,MATCH('2026'!B101,'Balance des comptes'!$A:$A,0)),0) -> 20017622 | D101: =IFERROR(INDEX('Balance des comptes'!$R:$R,MATCH('2026'!B101,'Balance des comptes'!$A:$A,0)),0) -> 0 | E101: =+C101-D101 -> 20017622
B102: Solde Trésorerie | C102: =SUM(C101:C101) -> 20017622 | D102: =SUM(D101:D101) -> 0 | E102: =SUM(E101:E101) -> 20017622
B104: Vérification | E104: =+E100+E102 -> 12212892
A110: JOVENA | C110: DEBIT | D110: CREDIT | E110: SOLDE
B111: 467150 | C111: =IFERROR(INDEX('Balance des comptes'!$O:$O,MATCH('2026'!B111,'Balance des comptes'!$A:$A,0)),0) -> 0 | D111: =IFERROR(INDEX('Balance des comptes'!$R:$R,MATCH('2026'!B111,'Balance des comptes'!$A:$A,0)),0) -> 11986974 | E111: =+C111-D111 -> -11986974
B112: 460150 | C112: =IFERROR(INDEX('Balance des comptes'!$O:$O,MATCH('2026'!B112,'Balance des comptes'!$A:$A,0)),0) -> 12307074 | D112: =IFERROR(INDEX('Balance des comptes'!$R:$R,MATCH('2026'!B112,'Balance des comptes'!$A:$A,0)),0) -> 0 | E112: =+C112-D112 -> 12307074
B113: 461150 | C113: =IFERROR(INDEX('Balance des comptes'!$O:$O,MATCH('2026'!B113,'Balance des comptes'!$A:$A,0)),0) -> 0 | D113: =IFERROR(INDEX('Balance des comptes'!$R:$R,MATCH('2026'!B113,'Balance des comptes'!$A:$A,0)),0) -> 0 | E113: =+C113-D113 -> 0
B114: 462150 | C114: =IFERROR(INDEX('Balance des comptes'!$O:$O,MATCH('2026'!B114,'Balance des comptes'!$A:$A,0)),0) -> 0 | D114: =IFERROR(INDEX('Balance des comptes'!$R:$R,MATCH('2026'!B114,'Balance des comptes'!$A:$A,0)),0) -> 320100 | E114: =+C114-D114 -> -320100
B115: Solde Appel de fonds | C115: =SUM(C111:C114) -> 12307074 | D115: =SUM(D111:D114) -> 12307074 | E115: =SUM(E111:E114) -> 0
B116: 512150 | C116: =IFERROR(INDEX('Balance des comptes'!$O:$O,MATCH('2026'!B116,'Balance des comptes'!$A:$A,0)),0) -> 219216.49 | D116: =IFERROR(INDEX('Balance des comptes'!$R:$R,MATCH('2026'!B116,'Balance des comptes'!$A:$A,0)),0) -> 0 | E116: =+C116-D116 -> 219216.49
B117: Solde Trésorerie | C117: =SUM(C116:C116) -> 219216.49 | D117: =SUM(D116:D116) -> 0 | E117: =SUM(E116:E116) -> 219216.49
B119: Vérification | E119: =+E115+E117 -> 219216.49
A121: MCB | C121: DEBIT | D121: CREDIT | E121: SOLDE
B122: 467180 | C122: =IFERROR(INDEX('Balance des comptes'!$O:$O,MATCH('2026'!B122,'Balance des comptes'!$A:$A,0)),0) -> 0 | D122: =IFERROR(INDEX('Balance des comptes'!$R:$R,MATCH('2026'!B122,'Balance des comptes'!$A:$A,0)),0) -> 22048639 | E122: =+C122-D122 -> -22048639
B123: 460180 | C123: =IFERROR(INDEX('Balance des comptes'!$O:$O,MATCH('2026'!B123,'Balance des comptes'!$A:$A,0)),0) -> 0 | D123: =IFERROR(INDEX('Balance des comptes'!$R:$R,MATCH('2026'!B123,'Balance des comptes'!$A:$A,0)),0) -> 0 | E123: =+C123-D123 -> 0
B124: 461180 | C124: =IFERROR(INDEX('Balance des comptes'!$O:$O,MATCH('2026'!B124,'Balance des comptes'!$A:$A,0)),0) -> 0 | D124: =IFERROR(INDEX('Balance des comptes'!$R:$R,MATCH('2026'!B124,'Balance des comptes'!$A:$A,0)),0) -> 0 | E124: =+C124-D124 -> 0
B125: 462180 | C125: =IFERROR(INDEX('Balance des comptes'!$O:$O,MATCH('2026'!B125,'Balance des comptes'!$A:$A,0)),0) -> 0 | D125: =IFERROR(INDEX('Balance des comptes'!$R:$R,MATCH('2026'!B125,'Balance des comptes'!$A:$A,0)),0) -> 1866240 | E125: =+C125-D125 -> -1866240
B126: Solde Appel de fonds | C126: =SUM(C121:C125) -> 0 | D126: =SUM(D122:D125) -> 23914879 | E126: =SUM(E122:E125) -> -23914879
B127: 512180 | C127: =IFERROR(INDEX('Balance des comptes'!$O:$O,MATCH('2026'!B127,'Balance des comptes'!$A:$A,0)),0) -> 24087679 | D127: =IFERROR(INDEX('Balance des comptes'!$R:$R,MATCH('2026'!B127,'Balance des comptes'!$A:$A,0)),0) -> 0 | E127: =+C127-D127 -> 24087679
B128: Solde Trésorerie | C128: =SUM(C127:C127) -> 24087679 | D128: =SUM(D127:D127) -> 0 | E128: =SUM(E127:E127) -> 24087679
...

Sheet Feuil1
A1: P | B1: Code journal | C1: Date | D1: N° pièce | E1: Référence | F1: N° facture | G1: N° compte tiers | H1: Libellé écriture | I1: Date échéance | J1: Lettrage montant | K1: Pointage | L1: Débit | M1: Crédit
A2: 0 | B2: RAN | C2: 45658 | D2: ="36" -> 36 | G2: CLTDHLEXPRESS | H2: A.N. au 010123 | M2: 80866901
A3: 0 | B3: RAN | C3: 45658 | D3: ="36" -> 36 | G3: FONDHLEXPRESS | H3: A.N. au 010123 | M3: 1.8592069e+08
A4: 0 | B4: OD | C4: 45666 | D4: ="80" -> 80 | E4: 45666 | G4: FONDHLEXPRESS | H4: COMPENSATION FOND-HONORAIRE-REG-2024-11-FA-DHL EXPRESS | L4: 3103598.9
A5: 0 | B5: TIERS | C5: 45658 | D5: ="83" -> 83 | E5: 45649 | F5: 24325/357091 | G5: FONDHLEXPRESS | H5: DHL EXPRESS DECEMBRE 2024- PHARMACIE PRINCIPALE- REG 24325/357091 | L5: 644160
A6: 0 | B6: TIERS | C6: 45658 | D6: ="83" -> 83 | E6: 45655 | F6: LOT24899/363018 | G6: FONDHLEXPRESS | H6: DHL EXPRESS DECEMBRE 2024- PHARMACIE PRINCIPALE- REG LOT24899/363018 | L6: 383600
A7: 0 | B7: TIERS | C7: 45658 | D7: ="83" -> 83 | E7: 45656 | F7: LOT24548/358721 | G7: FONDHLEXPRESS | H7: DHL EXPRESS DECEMBRE 2024- PHARMACIE PRINCIPALE- REG LOT24548/358721 | L7: 598720
A8: 0 | B8: TIERS | C8: 45658 | D8: ="330" -> 330 | E8: 45657 | F8: ="21739" -> 21739 | G8: FONDHLEXPRESS | H8: DHL EXPRESS DECEMBRE 2024- RAZAFIMANANTSOA TIANA NIRINA- RMBT 21739 | L8: 110000
A9: 0 | B9: TIERS | C9: 45658 | D9: ="330" -> 330 | E9: 45657 | F9: ="21740" -> 21740 | G9: FONDHLEXPRESS | H9: DHL EXPRESS DECEMBRE 2024- RANAIVO IONIMALALA- RMBT 21740 | L9: 798400
A10: 0 | B10: TIERS | C10: 45658 | D10: ="432" -> 432 | E10: 45629 | F10: ="344896" -> 344896 | G10: FONDHLEXPRESS | H10: DHL EXPRESS DECEMBRE 2024- LUXOPTICA- REG 344896 | L10: 547200
A11: 0 | B11: TIERS | C11: 45658 | D11: ="432" -> 432 | E11: 45629 | F11: 24/3715 | G11: FONDHLEXPRESS | H11: DHL EXPRESS DECEMBRE 2024- CLINIQUE NOA- REG 24/3715 | L11: 84000
A12: 0 | B12: TIERS | C12: 45658 | D12: ="432" -> 432 | E12: 45629 | F12: ="251256" -> 251256 | G12: FONDHLEXPRESS | H12: DHL EXPRESS DECEMBRE 2024- PHARMACIE DU ROI- REG 251256 | L12: 76320
A13: 0 | B13: TIERS | C13: 45658 | D13: ="432" -> 432 | E13: 45639 | F13: FGC/000234/2024 | G13: FONDHLEXPRESS | H13: DHL EXPRESS DECEMBRE 2024- PHARMACIE D'ANKADINDRATOMBO- REG FGC/00023 | L13: 156960
A14: 0 | B14: TIERS | C14: 45658 | D14: ="432" -> 432 | E14: 45639 | F14: 1906/24Y | G14: FONDHLEXPRESS | H14: DHL EXPRESS DECEMBRE 2024- PHARMACIE TSARASANDRY- REG 1906/24Y | L14: 30240
A15: 0 | B15: TIERS | C15: 45658 | D15: ="432" -> 432 | E15: 45639 | F15: 2024/179 | G15: FONDHLEXPRESS | H15: DHL EXPRESS DECEMBRE 2024- SP VISION- REG 2024/179 | L15: 140000
A16: 0 | B16: TIERS | C16: 45658 | D16: ="432" -> 432 | E16: 45639 | F16: 15761/278774 | G16: FONDHLEXPRESS | H16: DHL EXPRESS DECEMBRE 2024- PHARMACIE MANDROSOA- REG 15761/278774 | L16: 136640
A17: 0 | B17: TIERS | C17: 45658 | D17: ="432" -> 432 | E17: 45642 | F17: ="202404005" -> 202404005 | G17: FONDHLEXPRESS | H17: DHL EXPRESS DECEMBRE 2024- CENTRE MEDICAL AMBATOMENA- REG 202404005 | L17: 16000
A18: 0 | B18: TIERS | C18: 45658 | D18: ="432" -> 432 | E18: 45642 | F18: FAC 11052024 | G18: FONDHLEXPRESS | H18: DHL EXPRESS DECEMBRE 2024- DR MIRAFINARITRA RAFIDIARIMANANA- REG FAC | L18: 672000
A19: 0 | B19: TIERS | C19: 45658 | D19: ="432" -> 432 | E19: 45642 | F19: 1712/ALH/2024 | G19: FONDHLEXPRESS | H19: DHL EXPRESS DECEMBRE 2024- POLYCLINIQUE ILAFY- REG 1712/ALH/2024 | L19: 15200
A20: 0 | B20: TIERS | C20: 45658 | D20: ="432" -> 432 | E20: 45642 | F20: ="0124" -> 0124 | G20: FONDHLEXPRESS | H20: DHL EXPRESS DECEMBRE 2024- CENTRE MEDICAL COLISEUM- REG 0124 | L20: 148800
A21: 0 | B21: TIERS | C21: 45658 | D21: ="432" -> 432 | E21: 45649 | F21: ="41130" -> 41130 | G21: FONDHLEXPRESS | H21: DHL EXPRESS DECEMBRE 2024- CABINET NOOR (OPHTALMO)- REG 41130 | L21: 28000
A22: 0 | B22: TIERS | C22: 45658 | D22: ="432" -> 432 | E22: 45649 | F22: FAC 21052024 | G22: FONDHLEXPRESS | H22: DHL EXPRESS DECEMBRE 2024- EYE CARE (OPHTALMO)- REG FAC 21052024 | L22: 28000
A23: 0 | B23: TIERS | C23: 45658 | D23: ="432" -> 432 | E23: 45649 | F23: 1501/24/Y | G23: FONDHLEXPRESS | H23: DHL EXPRESS DECEMBRE 2024- PHARMACIE TSARASANDRY- REG 1501/24/Y | L23: 162160
A24: 0 | B24: TIERS | C24: 45658 | D24: ="432" -> 432 | E24: 45649 | F24: DC 060824 | G24: FONDHLEXPRESS | H24: DHL EXPRESS DECEMBRE 2024- PHARMACIE AMBOHIDRATRIMO- REG DC 060824 | L24: 19360
A25: 0 | B25: TIERS | C25: 45658 | D25: ="432" -> 432 | E25: 45649 | F25: ="343404" -> 343404 | G25: FONDHLEXPRESS | H25: DHL EXPRESS DECEMBRE 2024- LUXOPTICA- REG 343404 | L25: 1124224
A26: 0 | B26: TIERS | C26: 45658 | D26: ="432" -> 432 | E26: 45649 | F26: 24E02583 | G26: FONDHLEXPRESS | H26: DHL EXPRESS DECEMBRE 2024- HEALTH LABO- REG 24E02583 | L26: 227840
A27: 0 | B27: TIERS | C27: 45658 | D27: ="432" -> 432 | E27: 45649 | F27: 01/DHL 2024 | G27: FONDHLEXPRESS | H27: DHL EXPRESS DECEMBRE 2024- ESPACE MEDICAL ANTSIRABE- REG 01/DHL 2024 | L27: 165200
A28: 0 | B28: TIERS | C28: 45658 | D28: ="432" -> 432 | E28: 45649 | F28: 111490/PH/AV/2024 | G28: FONDHLEXPRESS | H28: DHL EXPRESS DECEMBRE 2024- PHARMACIE D'AVARADRANO- REG 111490/PH/AV/2 | L28: 1094880
A29: 0 | B29: TIERS | C29: 45658 | D29: ="432" -> 432 | E29: 45649 | F29: 07-2023/CSL | G29: FONDHLEXPRESS | H29: DHL EXPRESS DECEMBRE 2024- IMAGERIE DE LA CLINIQUE SAINT LAURENT - RE | L29: 48000
A30: 0 | B30: TIERS | C30: 45658 | D30: ="432" -> 432 | E30: 45649 | F30: VP-1051592 | G30: FONDHLEXPRESS | H30: DHL EXPRESS DECEMBRE 2024- PHARMACIE GRACE- REG VP-1051592 | L30: 455520
A31: 0 | B31: TIERS | C31: 45658 | D31: ="432" -> 432 | E31: 45649 | F31: 0924/003 | G31: FONDHLEXPRESS | H31: DHL EXPRESS DECEMBRE 2024- CENTRE MEDICAL COLISEUM- REG 0924/003 | L31: 24000
A32: 0 | B32: TIERS | C32: 45658 | D32: ="432" -> 432 | E32: 45649 | F32: FAC 26102024 | G32: FONDHLEXPRESS | H32: DHL EXPRESS DECEMBRE 2024- ZOOM OPTIQUE (OPHTALMO)- REG FAC 26102024 | L32: 56000
A33: 0 | B33: TIERS | C33: 45658 | D33: ="432" -> 432 | E33: 45649 | F33: ="17517" -> 17517 | G33: FONDHLEXPRESS | H33: DHL EXPRESS DECEMBRE 2024- ZOOM OPTIQUE- REG 17517 | L33: 609600
A34: 0 | B34: TIERS | C34: 45658 | D34: ="432" -> 432 | E34: 45649 | F34: IS 20 241 213 | G34: FONDHLEXPRESS | H34: DHL EXPRESS DECEMBRE 2024- CLINIQUE ET MATERNITE SAINT FRANCOIS D'ASS | L34: 32000
A35: 0 | B35: TIERS | C35: 45658 | D35: ="432" -> 432 | E35: 45649 | F35: FAC 02102024 | G35: FONDHLEXPRESS | H35: DHL EXPRESS DECEMBRE 2024- SAINT JOSEPH MEDICAL SERVICES- REG FAC 021 | L35: 12800
A36: 0 | B36: TIERS | C36: 45658 | D36: ="432" -> 432 | E36: 45649 | F36: 15838/279257 | G36: FONDHLEXPRESS | H36: DHL EXPRESS DECEMBRE 2024- PHARMACIE MANDROSOA- REG 15838/279257 | L36: 29520
A37: 0 | B37: TIERS | C37: 45658 | D37: ="432" -> 432 | E37: 45649 | F37: 24/64067 | G37: FONDHLEXPRESS | H37: DHL EXPRESS DECEMBRE 2024- CLINIQUE NOA- REG 24/64067 | L37: 28000
A38: 0 | B38: TIERS | C38: 45658 | D38: ="432" -> 432 | E38: 45652 | F38: FAC/126021/2024 | G38: FONDHLEXPRESS | H38: DHL EXPRESS DECEMBRE 2024- PHARMACIE D'ANKADINDRATOMBO- REG FAC/12602 | L38: 156400
A39: 0 | B39: TIERS | C39: 45658 | D39: ="432" -> 432 | E39: 45657 | F39: FAC 12122024 | G39: FONDHLEXPRESS | H39: DHL EXPRESS DECEMBRE 2024- EYE CARE (OPHTALMO)- REG FAC 12122024 | L39: 28000
A40: 0 | B40: TIERS | C40: 45658 | D40: ="432" -> 432 | E40: 45657 | F40: FS 374965 | G40: FONDHLEXPRESS | H40: DHL EXPRESS DECEMBRE 2024- MARIE STOPES MADAGASCAR TANA- REG FS 37496 | L40: 65600
A41: 0 | B41: TIERS | C41: 45658 | D41: ="432" -> 432 | E41: 45657 | F41: ="2093" -> 2093 | G41: FONDHLEXPRESS | H41: DHL EXPRESS DECEMBRE 2024- MADAME RAMEFISON ANJA - PAV 80- REG 2093 | L41: 400000
A42: 0 | B42: TIERS | C42: 45658 | D42: ="432" -> 432 | E42: 45657 | F42: 12/24/010 | G42: FONDHLEXPRESS | H42: DHL EXPRESS DECEMBRE 2024- VEL'OPTIC- REG 12/24/010 | L42: 2487200
A43: 0 | B43: TIERS | C43: 45658 | D43: ="432" -> 432 | E43: 45657 | F43: 12/24/022 | G43: FONDHLEXPRESS | H43: DHL EXPRESS DECEMBRE 2024- OPTICITY- REG 12/24/022 | L43: 388000
A44: 0 | B44: TIERS | C44: 45658 | D44: ="432" -> 432 | E44: 45657 | F44: 2024/0269-P-TOA | G44: FONDHLEXPRESS | H44: DHL EXPRESS DECEMBRE 2024- 5 SENSES TOAMASINA- REG 2024/0269-P-TOA | L44: 420280
A45: 0 | B45: TIERS | C45: 45658 | D45: ="432" -> 432 | E45: 45657 | F45: ="344172" -> 344172 | G45: FONDHLEXPRESS | H45: DHL EXPRESS DECEMBRE 2024- LUXOPTICA- REG 344172 | L45: 1169600
A46: 0 | B46: TIERS | C46: 45658 | D46: ="432" -> 432 | E46: 45657 | F46: ="17555" -> 17555 | G46: FONDHLEXPRESS | H46: DHL EXPRESS DECEMBRE 2024- ZOOM OPTIQUE- REG 17555 | L46: 720000
A47: 0 | B47: TIERS | C47: 45658 | D47: ="432" -> 432 | E47: 45657 | F47: 24123/24 | G47: FONDHLEXPRESS | H47: DHL EXPRESS DECEMBRE 2024- LE LUNETIER- REG 24123/24 | L47: 248000
A48: 0 | B48: TIERS | C48: 45658 | D48: ="432" -> 432 | E48: 45657 | F48: MDR/OP/73965 | G48: FONDHLEXPRESS | H48: DHL EXPRESS DECEMBRE 2024- CENTRE DE SANTE DR AGARWAL'S (OPHTALMO)- R | L48: 454000
A49: 0 | B49: TIERS | C49: 45658 | D49: ="432" -> 432 | E49: 45657 | F49: 007/NOV/VO | G49: FONDHLEXPRESS | H49: DHL EXPRESS DECEMBRE 2024- VEL'OPTIC (OPHTALMO)- REG 007/NOV/VO | L49: 96000
A50: 0 | B50: TIERS | C50: 45658 | D50: ="432" -> 432 | E50: 45657 | F50: 019/NOV/VV | G50: FONDHLEXPRESS | H50: DHL EXPRESS DECEMBRE 2024- VEL'VISION (OPHTALMO)- REG 019/NOV/VV | L50: 32000
A51: 0 | B51: TIERS | C51: 45658 | D51: ="432" -> 432 | E51: 45657 | F51: AA24-01695/F | G51: FONDHLEXPRESS | H51: DHL EXPRESS DECEMBRE 2024- INSTITUT PASTEUR DE MADAGASCAR- REG AA24-0 | L51: 881880
A52: 0 | B52: TIERS | C52: 45658 | D52: ="432" -> 432 | E52: 45657 | F52: FAC 31072024 | G52: FONDHLEXPRESS | H52: DHL EXPRESS DECEMBRE 2024- MATERNITE DU CENTRE REFERENCE MEDICAL- REG | L52: 1480000
A53: 0 | B53: TIERS | C53: 45658 | D53: ="432" -> 432 | E53: 45657 | F53: FAC/143659/2024 | G53: FONDHLEXPRESS | H53: DHL EXPRESS DECEMBRE 2024- PHARMACIE D'ANKADINDRATOMBO- REG FAC/14365 | L53: 152960
A54: 0 | B54: BOADHL | C54: 45685 | D54: ="518" -> 518 | E54: ="00013102" -> 00013102 | G54: FONDHLEXPRESS | H54: CK BOA N° 00013102 du 28/01/2025-DHL EXPRESS-COTISATION 4EM TRIM 2024 | L54: 19603483
A55: 0 | B55: BOADHL | C55: 45688 | D55: ="628" -> 628 | E55: 45688 | G55: FONDHLEXPRESS | H55: Frais de Tenue de Compte Mois de JANVIER 2025 | L55: 10800
A56: 0 | B56: BOADHL | C56: 45688 | D56: ="629" -> 629 | E56: 45808 | G56: FONDHLEXPRESS | H56: Commission de Mouvements Mois de JANVIER 2025 | L56: 44296.25
A57: 0 | B57: BOADHL | C57: 45673 | D57: ="630" -> 630 | E57: 45673 | G57: FONDHLEXPRESS | H57: FRAIS DHL DC 231224 291224 301224 | L57: 3000
A58: 0 | B58: BOADHL | C58: 45681 | D58: ="631" -> 631 | E58: 45681 | G58: FONDHLEXPRESS | H58: FRAIS DHL DC 031224 131224 161224 231224 261224 311224 | L58: 3000
A59: 0 | B59: TIERS | C59: 45658 | D59: ="889" -> 889 | E59: 45647 | F59: 004/AOUT/VV/2024/ | G59: FONDHLEXPRESS | H59: DHL EXPRESS DECEMBRE 2024- VEL'VISION (OPHTALMO)- REG 004/AOUT/VV/202 | L59: 32000
A60: 0 | B60: TIERS | C60: 45658 | D60: ="889" -> 889 | E60: 45657 | F60: FAC112007/1/PH/AV | G60: FONDHLEXPRESS | H60: DHL EXPRESS DECEMBRE 2024- PHARMACIE D'AVARADRANO- REG FAC112007/1/PH | L60: 1237520
A61: 0 | B61: TIERS | C61: 45658 | D61: ="889" -> 889 | E61: 45657 | F61: FAC/170572/2024 | G61: FONDHLEXPRESS | H61: DHL EXPRESS DECEMBRE 2024- PHARMACIE D'ANKADINDRATOMBO- REG FAC/17057 | L61: 29120
A62: 0 | B62: TIERS | C62: 45658 | D62: ="889" -> 889 | E62: 45657 | F62: FC413032 | G62: FONDHLEXPRESS | H62: DHL EXPRESS DECEMBRE 2024- PHARMACIE METROPOLE- REG FC413032 | L62: 82880
A63: 0 | B63: TIERS | C63: 45658 | D63: ="889" -> 889 | E63: 45657 | F63: FAC17/12/24 | G63: FONDHLEXPRESS | H63: DHL EXPRESS DECEMBRE 2024- PHARMACIE D'AMBOHIDRATRIMO- REG FAC17/12/2 | L63: 72800
A64: 0 | B64: TIERS | C64: 45658 | D64: ="889" -> 889 | E64: 45657 | F64: VP-1069917 | G64: FONDHLEXPRESS | H64: DHL EXPRESS DECEMBRE 2024- PHARMACIE GRACE- REG VP-1069917 | L64: 506960
A65: 0 | B65: TIERS | C65: 45658 | D65: ="889" -> 889 | E65: 45657 | F65: FAC001576 | G65: FONDHLEXPRESS | H65: DHL EXPRESS DECEMBRE 2024- PHARMACIE D'IVATO- REG FAC001576 | L65: 60800
A66: 0 | B66: TIERS | C66: 45658 | D66: ="889" -> 889 | E66: 45657 | F66: FAC252916 | G66: FONDHLEXPRESS | H66: DHL EXPRESS DECEMBRE 2024- PHARMACIE DU ROI- REG FAC252916 | L66: 10080
A67: 0 | B67: TIERS | C67: 45658 | D67: ="889" -> 889 | E67: 45657 | F67: FAC1688/24Y | G67: FONDHLEXPRESS | H67: DHL EXPRESS DECEMBRE 2024- PHARMACIE TSARASANDRY- REG FAC1688/24Y | L67: 30320
A68: 0 | B68: TIERS | C68: 45658 | D68: ="889" -> 889 | E68: 45657 | F68: FAC359705 | G68: FONDHLEXPRESS | H68: DHL EXPRESS DECEMBRE 2024- PHARMACIE PRINCIPALE- REG FAC359705 | L68: 78160
A69: 0 | B69: TIERS | C69: 45658 | D69: ="889" -> 889 | E69: 45657 | F69: FAC/077724/2024 | G69: FONDHLEXPRESS | H69: DHL EXPRESS DECEMBRE 2024- PHARMACIE NY ANTSIKA- REG FAC/077724/2024 | L69: 30640
A70: 0 | B70: TIERS | C70: 45674 | D70: ="890" -> 890 | E70: 45674 | F70: ="21900" -> 21900 | G70: FONDHLEXPRESS | H70: DHL EXPRESS JANVIER 2025- RAZAFIMAMONJY MIRANA- RMBT 21900 | L70: 19280
A71: 0 | B71: TIERS | C71: 45688 | D71: ="1048" -> 1048 | E71: 45688 | F71: FAC06012025 | G71: FONDHLEXPRESS | H71: DHL EXPRESS JANVIER 2025- CENTRE DE SANTE BE NY SOA- REG FAC06012025 | L71: 185600
A72: 0 | B72: TIERS | C72: 45688 | D72: ="1048" -> 1048 | E72: 45688 | F72: 0125/001 | G72: FONDHLEXPRESS | H72: DHL EXPRESS JANVIER 2025- CENTRE MEDICAL COLISEUM- REG 0125/001 | L72: 124800
A73: 0 | B73: TIERS | C73: 45688 | D73: ="1048" -> 1048 | E73: 45688 | F73: 24/7589 | G73: FONDHLEXPRESS | H73: DHL EXPRESS JANVIER 2025- CLINIQUE NOA- REG 24/7589 | L73: 2045513
A74: 0 | B74: TIERS | C74: 45688 | D74: ="1048" -> 1048 | E74: 45688 | F74: FAC07012025 | G74: FONDHLEXPRESS | H74: DHL EXPRESS JANVIER 2025- EYE CARE (OPHTALMO)- REG FAC07012025 | L74: 739360
A75: 0 | B75: TIERS | C75: 45688 | D75: ="1048" -> 1048 | E75: 45688 | F75: MDR/OP/77263 | G75: FONDHLEXPRESS | H75: DHL EXPRESS JANVIER 2025- CENTRE DE SANTE DR AGARWAL'S - REG MDR/OP/7 | L75: 160000
A76: 0 | B76: TIERS | C76: 45688 | D76: ="1048" -> 1048 | E76: 45688 | F76: FAC24-50603 | G76: FONDHLEXPRESS | H76: DHL EXPRESS JANVIER 2025- IMAGERIE INSTITUT MEDICAL DE MADAG- REG FAC | L76: 674800
A77: 0 | B77: TIERS | C77: 45688 | D77: ="1048" -> 1048 | E77: 45688 | F77: AA24-01784/F | G77: FONDHLEXPRESS | H77: DHL EXPRESS JANVIER 2025- INSTITUT PASTEUR DE MADAGASCAR- REG AA24-01 | L77: 1169460
A78: 0 | B78: TIERS | C78: 45688 | D78: ="1048" -> 1048 | E78: 45688 | F78: FAC06112024 | G78: FONDHLEXPRESS | H78: DHL EXPRESS JANVIER 2025- MATERNITE DU CENTRE REFERENCE MEDICAL- REG | L78: 40000
A79: 0 | B79: TIERS | C79: 45688 | D79: ="1048" -> 1048 | E79: 45688 | F79: FACT/027270 | G79: FONDHLEXPRESS | H79: DHL EXPRESS JANVIER 2025- ORL AUDIOLOGY CLINIC AMBOHIBAO- REG FACT/02 | L79: 32000
A80: 0 | B80: TIERS | C80: 45688 | D80: ="1048" -> 1048 | E80: 45688 | F80: ="2836" -> 2836 | G80: FONDHLEXPRESS | H80: DHL EXPRESS JANVIER 2025- PHARMACIE COLISEUM- REG 2836 | L80: 102320
A81: 0 | B81: TIERS | C81: 45688 | D81: ="1048" -> 1048 | E81: 45688 | F81: FAC/030766/2024 | G81: FONDHLEXPRESS | H81: DHL EXPRESS JANVIER 2025- PHARMACIE CROIX DU SUD- REG FAC/030766/2024 | L81: 37040
A82: 0 | B82: TIERS | C82: 45688 | D82: ="1048" -> 1048 | E82: 45688 | F82: 112870/PH/AV/2024 | G82: FONDHLEXPRESS | H82: DHL EXPRESS JANVIER 2025- PHARMACIE D'AVARADRANO- REG 112870/PH/AV/20 | L82: 181520
A83: 0 | B83: TIERS | C83: 45688 | D83: ="1048" -> 1048 | E83: 45688 | F83: ="001778" -> 001778 | G83: FONDHLEXPRESS | H83: DHL EXPRESS JANVIER 2025- PHARMACIE D'IVATO- REG 001778 | L83: 164720
A84: 0 | B84: TIERS | C84: 45688 | D84: ="1048" -> 1048 | E84: 45688 | F84: VP-1079347 | G84: FONDHLEXPRESS | H84: DHL EXPRESS JANVIER 2025- PHARMACIE GRACE- REG VP-1079347 | L84: 406080
A85: 0 | B85: TIERS | C85: 45688 | D85: ="1048" -> 1048 | E85: 45688 | F85: LOT5877/279510 | G85: FONDHLEXPRESS | H85: DHL EXPRESS JANVIER 2025- PHARMACIE MANDROSOA- REG LOT5877/279510 | L85: 64800
A86: 0 | B86: TIERS | C86: 45688 | D86: ="1048" -> 1048 | E86: 45688 | F86: LOT24931/363268 | G86: FONDHLEXPRESS | H86: DHL EXPRESS JANVIER 2025- PHARMACIE PRINCIPALE- REG LOT24931/363268 | L86: 202080
A87: 0 | B87: TIERS | C87: 45688 | D87: ="1048" -> 1048 | E87: 45688 | F87: 000020/24Y | G87: FONDHLEXPRESS | H87: DHL EXPRESS JANVIER 2025- PHARMACIE TOKY- REG 000020/24Y | L87: 18560
A88: 0 | B88: TIERS | C88: 45688 | D88: ="1048" -> 1048 | E88: 45688 | F88: FAC14062024 | G88: FONDHLEXPRESS | H88: DHL EXPRESS JANVIER 2025- SAINT JOSEPH MEDICAL SERVICES- REG FAC14062 | L88: 16000
A89: 0 | B89: TIERS | C89: 45688 | D89: ="1048" -> 1048 | E89: 45688 | F89: 12/24/095 | G89: FONDHLEXPRESS | H89: DHL EXPRESS JANVIER 2025- VEL'OPTIC- REG 12/24/095 | L89: 1000000
A90: 0 | B90: TIERS | C90: 45688 | D90: ="1048" -> 1048 | E90: 45688 | F90: 004/JANVIER/VV/20 | G90: FONDHLEXPRESS | H90: DHL EXPRESS JANVIER 2025- VEL'VISION (OPHTALMO)- REG 004/JANVIER/VV/2 | L90: 96000
A91: 0 | B91: TIERS | C91: 45695 | D91: ="1651" -> 1651 | E91: 45695 | F91: ="22073" -> 22073 | G91: FONDHLEXPRESS | H91: DHL EXPRESS FEVRIER 2025- RAKOTONANAHARY EDMOND HERVÃ‰- RMBT 22073 | L91: 162018
A92: 0 | B92: TIERS | C92: 45689 | D92: ="1653" -> 1653 | E92: 45689 | F92: ="22024" -> 22024 | G92: FONDHLEXPRESS | H92: DHL EXPRESS FEVRIER 2025- RAKOTONANAHARY EDMOND HERVÃ‰- RMBT 22024 | L92: 1825000
A93: 0 | B93: TIERS | C93: 45709 | D93: ="2042" -> 2042 | E93: 45709 | F93: ="22374" -> 22374 | G93: FONDHLEXPRESS | H93: DHL EXPRESS FEVRIER 2025- RASAMOELINIAINA LINDA FAMENONTSOA- RMBT 223 | L93: 535240
A94: 0 | B94: MVOMCI | C94: 45716 | D94: ="2077" -> 2077 | E94: 45716 | F94: ="22374" -> 22374 | G94: FONDHLEXPRESS | H94: Frais DHL EXPRESS FEVRIER 2025- RASAMOELINIAINA LINDA FAMENONTSOA- RM | L94: 2500
A95: 0 | B95: BOADHL | C95: 45716 | D95: ="2094" -> 2094 | E95: 45716 | G95: FONDHLEXPRESS | H95: Frais de Tenue de Compte Mois de FEVRIER 2025 | L95: 10800
A96: 0 | B96: BOADHL | C96: 45716 | D96: ="2095" -> 2095 | E96: 45716 | G96: FONDHLEXPRESS | H96: Commission de Mouvements Mois de FEVRIER 2025 | L96: 78959.28
A97: 0 | B97: BOADHL | C97: 45698 | D97: ="2097" -> 2097 | E97: 45698 | G97: FONDHLEXPRESS | H97: FRAIS DHL DC 211224 311224 | L97: 3000
A98: 0 | B98: BOADHL | C98: 45698 | D98: ="2099" -> 2099 | E98: 45698 | G98: FONDHLEXPRESS | H98: Frais DHL EXPRESS JANVIER 2025- RAZAFIMAMONJY MIRANA- RMBT 21900 | L98: 9600
A99: 0 | B99: BOADHL | C99: 45706 | D99: ="2100" -> 2100 | E99: 45706 | G99: FONDHLEXPRESS | H99: FRAIS DHL DC 310125 | L99: 3000
A100: 0 | B100: BOADHL | C100: 45709 | D100: ="2101" -> 2101 | E100: 45709 | G100: FONDHLEXPRESS | H100: Frais DHL EXPRESS FEVRIER 2025- RAKOTONANAHARY EDMOND HERVÃ‰- RMBT 22 | L100: 9600
...

Sheet Feuil2
A1: P | B1: Code journal | C1: Date | D1: N° pièce | E1: Référence | F1: N° facture | G1: N° compte tiers | H1: Libellé écriture | I1: Date échéance | J1: Lettrage montant | K1: Pointage | L1: Débit | M1: Crédit
A2: 0 | B2: RAN | C2: 45658 | D2: ="36" -> 36 | G2: CLTDHLEXPRESS | H2: A.N. au 010123 | M2: 80866901
A3: 0 | B3: RAN | C3: 45658 | D3: ="36" -> 36 | G3: FONDHLEXPRESS | H3: A.N. au 010123 | M3: 1.8592069e+08
A4: 0 | B4: OD | C4: 45666 | D4: ="80" -> 80 | E4: 45666 | G4: FONDHLEXPRESS | H4: COMPENSATION FOND-HONORAIRE-REG-2024-11-FA-DHL EXPRESS | L4: 3103598.9
A5: 0 | B5: TIERS | C5: 45658 | D5: ="83" -> 83 | E5: 45649 | F5: 24325/357091 | G5: FONDHLEXPRESS | H5: DHL EXPRESS DECEMBRE 2024- PHARMACIE PRINCIPALE- REG 24325/357091 | L5: 644160
A6: 0 | B6: TIERS | C6: 45658 | D6: ="83" -> 83 | E6: 45655 | F6: LOT24899/363018 | G6: FONDHLEXPRESS | H6: DHL EXPRESS DECEMBRE 2024- PHARMACIE PRINCIPALE- REG LOT24899/363018 | L6: 383600
A7: 0 | B7: TIERS | C7: 45658 | D7: ="83" -> 83 | E7: 45656 | F7: LOT24548/358721 | G7: FONDHLEXPRESS | H7: DHL EXPRESS DECEMBRE 2024- PHARMACIE PRINCIPALE- REG LOT24548/358721 | L7: 598720
A8: 0 | B8: TIERS | C8: 45658 | D8: ="330" -> 330 | E8: 45657 | F8: ="21739" -> 21739 | G8: FONDHLEXPRESS | H8: DHL EXPRESS DECEMBRE 2024- RAZAFIMANANTSOA TIANA NIRINA- RMBT 21739 | L8: 110000
A9: 0 | B9: TIERS | C9: 45658 | D9: ="330" -> 330 | E9: 45657 | F9: ="21740" -> 21740 | G9: FONDHLEXPRESS | H9: DHL EXPRESS DECEMBRE 2024- RANAIVO IONIMALALA- RMBT 21740 | L9: 798400
A10: 0 | B10: TIERS | C10: 45658 | D10: ="432" -> 432 | E10: 45629 | F10: ="344896" -> 344896 | G10: FONDHLEXPRESS | H10: DHL EXPRESS DECEMBRE 2024- LUXOPTICA- REG 344896 | L10: 547200
A11: 0 | B11: TIERS | C11: 45658 | D11: ="432" -> 432 | E11: 45629 | F11: 24/3715 | G11: FONDHLEXPRESS | H11: DHL EXPRESS DECEMBRE 2024- CLINIQUE NOA- REG 24/3715 | L11: 84000
A12: 0 | B12: TIERS | C12: 45658 | D12: ="432" -> 432 | E12: 45629 | F12: ="251256" -> 251256 | G12: FONDHLEXPRESS | H12: DHL EXPRESS DECEMBRE 2024- PHARMACIE DU ROI- REG 251256 | L12: 76320
A13: 0 | B13: TIERS | C13: 45658 | D13: ="432" -> 432 | E13: 45639 | F13: FGC/000234/2024 | G13: FONDHLEXPRESS | H13: DHL EXPRESS DECEMBRE 2024- PHARMACIE D'ANKADINDRATOMBO- REG FGC/00023 | L13: 156960
A14: 0 | B14: TIERS | C14: 45658 | D14: ="432" -> 432 | E14: 45639 | F14: 1906/24Y | G14: FONDHLEXPRESS | H14: DHL EXPRESS DECEMBRE 2024- PHARMACIE TSARASANDRY- REG 1906/24Y | L14: 30240
A15: 0 | B15: TIERS | C15: 45658 | D15: ="432" -> 432 | E15: 45639 | F15: 2024/179 | G15: FONDHLEXPRESS | H15: DHL EXPRESS DECEMBRE 2024- SP VISION- REG 2024/179 | L15: 140000
A16: 0 | B16: TIERS | C16: 45658 | D16: ="432" -> 432 | E16: 45639 | F16: 15761/278774 | G16: FONDHLEXPRESS | H16: DHL EXPRESS DECEMBRE 2024- PHARMACIE MANDROSOA- REG 15761/278774 | L16: 136640
A17: 0 | B17: TIERS | C17: 45658 | D17: ="432" -> 432 | E17: 45642 | F17: ="202404005" -> 202404005 | G17: FONDHLEXPRESS | H17: DHL EXPRESS DECEMBRE 2024- CENTRE MEDICAL AMBATOMENA- REG 202404005 | L17: 16000
A18: 0 | B18: TIERS | C18: 45658 | D18: ="432" -> 432 | E18: 45642 | F18: FAC 11052024 | G18: FONDHLEXPRESS | H18: DHL EXPRESS DECEMBRE 2024- DR MIRAFINARITRA RAFIDIARIMANANA- REG FAC | L18: 672000
A19: 0 | B19: TIERS | C19: 45658 | D19: ="432" -> 432 | E19: 45642 | F19: 1712/ALH/2024 | G19: FONDHLEXPRESS | H19: DHL EXPRESS DECEMBRE 2024- POLYCLINIQUE ILAFY- REG 1712/ALH/2024 | L19: 15200
A20: 0 | B20: TIERS | C20: 45658 | D20: ="432" -> 432 | E20: 45642 | F20: ="0124" -> 0124 | G20: FONDHLEXPRESS | H20: DHL EXPRESS DECEMBRE 2024- CENTRE MEDICAL COLISEUM- REG 0124 | L20: 148800
A21: 0 | B21: TIERS | C21: 45658 | D21: ="432" -> 432 | E21: 45649 | F21: ="41130" -> 41130 | G21: FONDHLEXPRESS | H21: DHL EXPRESS DECEMBRE 2024- CABINET NOOR (OPHTALMO)- REG 41130 | L21: 28000
A22: 0 | B22: TIERS | C22: 45658 | D22: ="432" -> 432 | E22: 45649 | F22: FAC 21052024 | G22: FONDHLEXPRESS | H22: DHL EXPRESS DECEMBRE 2024- EYE CARE (OPHTALMO)- REG FAC 21052024 | L22: 28000
A23: 0 | B23: TIERS | C23: 45658 | D23: ="432" -> 432 | E23: 45649 | F23: 1501/24/Y | G23: FONDHLEXPRESS | H23: DHL EXPRESS DECEMBRE 2024- PHARMACIE TSARASANDRY- REG 1501/24/Y | L23: 162160
A24: 0 | B24: TIERS | C24: 45658 | D24: ="432" -> 432 | E24: 45649 | F24: DC 060824 | G24: FONDHLEXPRESS | H24: DHL EXPRESS DECEMBRE 2024- PHARMACIE AMBOHIDRATRIMO- REG DC 060824 | L24: 19360
A25: 0 | B25: TIERS | C25: 45658 | D25: ="432" -> 432 | E25: 45649 | F25: ="343404" -> 343404 | G25: FONDHLEXPRESS | H25: DHL EXPRESS DECEMBRE 2024- LUXOPTICA- REG 343404 | L25: 1124224
A26: 0 | B26: TIERS | C26: 45658 | D26: ="432" -> 432 | E26: 45649 | F26: 24E02583 | G26: FONDHLEXPRESS | H26: DHL EXPRESS DECEMBRE 2024- HEALTH LABO- REG 24E02583 | L26: 227840
A27: 0 | B27: TIERS | C27: 45658 | D27: ="432" -> 432 | E27: 45649 | F27: 01/DHL 2024 | G27: FONDHLEXPRESS | H27: DHL EXPRESS DECEMBRE 2024- ESPACE MEDICAL ANTSIRABE- REG 01/DHL 2024 | L27: 165200
A28: 0 | B28: TIERS | C28: 45658 | D28: ="432" -> 432 | E28: 45649 | F28: 111490/PH/AV/2024 | G28: FONDHLEXPRESS | H28: DHL EXPRESS DECEMBRE 2024- PHARMACIE D'AVARADRANO- REG 111490/PH/AV/2 | L28: 1094880
A29: 0 | B29: TIERS | C29: 45658 | D29: ="432" -> 432 | E29: 45649 | F29: 07-2023/CSL | G29: FONDHLEXPRESS | H29: DHL EXPRESS DECEMBRE 2024- IMAGERIE DE LA CLINIQUE SAINT LAURENT - RE | L29: 48000
A30: 0 | B30: TIERS | C30: 45658 | D30: ="432" -> 432 | E30: 45649 | F30: VP-1051592 | G30: FONDHLEXPRESS | H30: DHL EXPRESS DECEMBRE 2024- PHARMACIE GRACE- REG VP-1051592 | L30: 455520
A31: 0 | B31: TIERS | C31: 45658 | D31: ="432" -> 432 | E31: 45649 | F31: 0924/003 | G31: FONDHLEXPRESS | H31: DHL EXPRESS DECEMBRE 2024- CENTRE MEDICAL COLISEUM- REG 0924/003 | L31: 24000
A32: 0 | B32: TIERS | C32: 45658 | D32: ="432" -> 432 | E32: 45649 | F32: FAC 26102024 | G32: FONDHLEXPRESS | H32: DHL EXPRESS DECEMBRE 2024- ZOOM OPTIQUE (OPHTALMO)- REG FAC 26102024 | L32: 56000
A33: 0 | B33: TIERS | C33: 45658 | D33: ="432" -> 432 | E33: 45649 | F33: ="17517" -> 17517 | G33: FONDHLEXPRESS | H33: DHL EXPRESS DECEMBRE 2024- ZOOM OPTIQUE- REG 17517 | L33: 609600
A34: 0 | B34: TIERS | C34: 45658 | D34: ="432" -> 432 | E34: 45649 | F34: IS 20 241 213 | G34: FONDHLEXPRESS | H34: DHL EXPRESS DECEMBRE 2024- CLINIQUE ET MATERNITE SAINT FRANCOIS D'ASS | L34: 32000
A35: 0 | B35: TIERS | C35: 45658 | D35: ="432" -> 432 | E35: 45649 | F35: FAC 02102024 | G35: FONDHLEXPRESS | H35: DHL EXPRESS DECEMBRE 2024- SAINT JOSEPH MEDICAL SERVICES- REG FAC 021 | L35: 12800
A36: 0 | B36: TIERS | C36: 45658 | D36: ="432" -> 432 | E36: 45649 | F36: 15838/279257 | G36: FONDHLEXPRESS | H36: DHL EXPRESS DECEMBRE 2024- PHARMACIE MANDROSOA- REG 15838/279257 | L36: 29520
A37: 0 | B37: TIERS | C37: 45658 | D37: ="432" -> 432 | E37: 45649 | F37: 24/64067 | G37: FONDHLEXPRESS | H37: DHL EXPRESS DECEMBRE 2024- CLINIQUE NOA- REG 24/64067 | L37: 28000
A38: 0 | B38: TIERS | C38: 45658 | D38: ="432" -> 432 | E38: 45652 | F38: FAC/126021/2024 | G38: FONDHLEXPRESS | H38: DHL EXPRESS DECEMBRE 2024- PHARMACIE D'ANKADINDRATOMBO- REG FAC/12602 | L38: 156400
A39: 0 | B39: TIERS | C39: 45658 | D39: ="432" -> 432 | E39: 45657 | F39: FAC 12122024 | G39: FONDHLEXPRESS | H39: DHL EXPRESS DECEMBRE 2024- EYE CARE (OPHTALMO)- REG FAC 12122024 | L39: 28000
A40: 0 | B40: TIERS | C40: 45658 | D40: ="432" -> 432 | E40: 45657 | F40: FS 374965 | G40: FONDHLEXPRESS | H40: DHL EXPRESS DECEMBRE 2024- MARIE STOPES MADAGASCAR TANA- REG FS 37496 | L40: 65600
A41: 0 | B41: TIERS | C41: 45658 | D41: ="432" -> 432 | E41: 45657 | F41: ="2093" -> 2093 | G41: FONDHLEXPRESS | H41: DHL EXPRESS DECEMBRE 2024- MADAME RAMEFISON ANJA - PAV 80- REG 2093 | L41: 400000
A42: 0 | B42: TIERS | C42: 45658 | D42: ="432" -> 432 | E42: 45657 | F42: 12/24/010 | G42: FONDHLEXPRESS | H42: DHL EXPRESS DECEMBRE 2024- VEL'OPTIC- REG 12/24/010 | L42: 2487200
A43: 0 | B43: TIERS | C43: 45658 | D43: ="432" -> 432 | E43: 45657 | F43: 12/24/022 | G43: FONDHLEXPRESS | H43: DHL EXPRESS DECEMBRE 2024- OPTICITY- REG 12/24/022 | L43: 388000
A44: 0 | B44: TIERS | C44: 45658 | D44: ="432" -> 432 | E44: 45657 | F44: 2024/0269-P-TOA | G44: FONDHLEXPRESS | H44: DHL EXPRESS DECEMBRE 2024- 5 SENSES TOAMASINA- REG 2024/0269-P-TOA | L44: 420280
A45: 0 | B45: TIERS | C45: 45658 | D45: ="432" -> 432 | E45: 45657 | F45: ="344172" -> 344172 | G45: FONDHLEXPRESS | H45: DHL EXPRESS DECEMBRE 2024- LUXOPTICA- REG 344172 | L45: 1169600
A46: 0 | B46: TIERS | C46: 45658 | D46: ="432" -> 432 | E46: 45657 | F46: ="17555" -> 17555 | G46: FONDHLEXPRESS | H46: DHL EXPRESS DECEMBRE 2024- ZOOM OPTIQUE- REG 17555 | L46: 720000
A47: 0 | B47: TIERS | C47: 45658 | D47: ="432" -> 432 | E47: 45657 | F47: 24123/24 | G47: FONDHLEXPRESS | H47: DHL EXPRESS DECEMBRE 2024- LE LUNETIER- REG 24123/24 | L47: 248000
A48: 0 | B48: TIERS | C48: 45658 | D48: ="432" -> 432 | E48: 45657 | F48: MDR/OP/73965 | G48: FONDHLEXPRESS | H48: DHL EXPRESS DECEMBRE 2024- CENTRE DE SANTE DR AGARWAL'S (OPHTALMO)- R | L48: 454000
A49: 0 | B49: TIERS | C49: 45658 | D49: ="432" -> 432 | E49: 45657 | F49: 007/NOV/VO | G49: FONDHLEXPRESS | H49: DHL EXPRESS DECEMBRE 2024- VEL'OPTIC (OPHTALMO)- REG 007/NOV/VO | L49: 96000
A50: 0 | B50: TIERS | C50: 45658 | D50: ="432" -> 432 | E50: 45657 | F50: 019/NOV/VV | G50: FONDHLEXPRESS | H50: DHL EXPRESS DECEMBRE 2024- VEL'VISION (OPHTALMO)- REG 019/NOV/VV | L50: 32000
A51: 0 | B51: TIERS | C51: 45658 | D51: ="432" -> 432 | E51: 45657 | F51: AA24-01695/F | G51: FONDHLEXPRESS | H51: DHL EXPRESS DECEMBRE 2024- INSTITUT PASTEUR DE MADAGASCAR- REG AA24-0 | L51: 881880
A52: 0 | B52: TIERS | C52: 45658 | D52: ="432" -> 432 | E52: 45657 | F52: FAC 31072024 | G52: FONDHLEXPRESS | H52: DHL EXPRESS DECEMBRE 2024- MATERNITE DU CENTRE REFERENCE MEDICAL- REG | L52: 1480000
A53: 0 | B53: TIERS | C53: 45658 | D53: ="432" -> 432 | E53: 45657 | F53: FAC/143659/2024 | G53: FONDHLEXPRESS | H53: DHL EXPRESS DECEMBRE 2024- PHARMACIE D'ANKADINDRATOMBO- REG FAC/14365 | L53: 152960
A54: 0 | B54: BOADHL | C54: 45685 | D54: ="518" -> 518 | E54: ="00013102" -> 00013102 | G54: FONDHLEXPRESS | H54: CK BOA N° 00013102 du 28/01/2025-DHL EXPRESS-COTISATION 4EM TRIM 2024 | L54: 19603483
A55: 0 | B55: BOADHL | C55: 45688 | D55: ="628" -> 628 | E55: 45688 | G55: FONDHLEXPRESS | H55: Frais de Tenue de Compte Mois de JANVIER 2025 | L55: 10800
A56: 0 | B56: BOADHL | C56: 45688 | D56: ="629" -> 629 | E56: 45808 | G56: FONDHLEXPRESS | H56: Commission de Mouvements Mois de JANVIER 2025 | L56: 44296.25
A57: 0 | B57: BOADHL | C57: 45673 | D57: ="630" -> 630 | E57: 45673 | G57: FONDHLEXPRESS | H57: FRAIS DHL DC 231224 291224 301224 | L57: 3000
A58: 0 | B58: BOADHL | C58: 45681 | D58: ="631" -> 631 | E58: 45681 | G58: FONDHLEXPRESS | H58: FRAIS DHL DC 031224 131224 161224 231224 261224 311224 | L58: 3000
A59: 0 | B59: TIERS | C59: 45658 | D59: ="889" -> 889 | E59: 45647 | F59: 004/AOUT/VV/2024/ | G59: FONDHLEXPRESS | H59: DHL EXPRESS DECEMBRE 2024- VEL'VISION (OPHTALMO)- REG 004/AOUT/VV/202 | L59: 32000
A60: 0 | B60: TIERS | C60: 45658 | D60: ="889" -> 889 | E60: 45657 | F60: FAC112007/1/PH/AV | G60: FONDHLEXPRESS | H60: DHL EXPRESS DECEMBRE 2024- PHARMACIE D'AVARADRANO- REG FAC112007/1/PH | L60: 1237520
A61: 0 | B61: TIERS | C61: 45658 | D61: ="889" -> 889 | E61: 45657 | F61: FAC/170572/2024 | G61: FONDHLEXPRESS | H61: DHL EXPRESS DECEMBRE 2024- PHARMACIE D'ANKADINDRATOMBO- REG FAC/17057 | L61: 29120
A62: 0 | B62: TIERS | C62: 45658 | D62: ="889" -> 889 | E62: 45657 | F62: FC413032 | G62: FONDHLEXPRESS | H62: DHL EXPRESS DECEMBRE 2024- PHARMACIE METROPOLE- REG FC413032 | L62: 82880
A63: 0 | B63: TIERS | C63: 45658 | D63: ="889" -> 889 | E63: 45657 | F63: FAC17/12/24 | G63: FONDHLEXPRESS | H63: DHL EXPRESS DECEMBRE 2024- PHARMACIE D'AMBOHIDRATRIMO- REG FAC17/12/2 | L63: 72800
A64: 0 | B64: TIERS | C64: 45658 | D64: ="889" -> 889 | E64: 45657 | F64: VP-1069917 | G64: FONDHLEXPRESS | H64: DHL EXPRESS DECEMBRE 2024- PHARMACIE GRACE- REG VP-1069917 | L64: 506960
A65: 0 | B65: TIERS | C65: 45658 | D65: ="889" -> 889 | E65: 45657 | F65: FAC001576 | G65: FONDHLEXPRESS | H65: DHL EXPRESS DECEMBRE 2024- PHARMACIE D'IVATO- REG FAC001576 | L65: 60800
A66: 0 | B66: TIERS | C66: 45658 | D66: ="889" -> 889 | E66: 45657 | F66: FAC252916 | G66: FONDHLEXPRESS | H66: DHL EXPRESS DECEMBRE 2024- PHARMACIE DU ROI- REG FAC252916 | L66: 10080
A67: 0 | B67: TIERS | C67: 45658 | D67: ="889" -> 889 | E67: 45657 | F67: FAC1688/24Y | G67: FONDHLEXPRESS | H67: DHL EXPRESS DECEMBRE 2024- PHARMACIE TSARASANDRY- REG FAC1688/24Y | L67: 30320
A68: 0 | B68: TIERS | C68: 45658 | D68: ="889" -> 889 | E68: 45657 | F68: FAC359705 | G68: FONDHLEXPRESS | H68: DHL EXPRESS DECEMBRE 2024- PHARMACIE PRINCIPALE- REG FAC359705 | L68: 78160
A69: 0 | B69: TIERS | C69: 45658 | D69: ="889" -> 889 | E69: 45657 | F69: FAC/077724/2024 | G69: FONDHLEXPRESS | H69: DHL EXPRESS DECEMBRE 2024- PHARMACIE NY ANTSIKA- REG FAC/077724/2024 | L69: 30640
A70: 0 | B70: TIERS | C70: 45674 | D70: ="890" -> 890 | E70: 45674 | F70: ="21900" -> 21900 | G70: FONDHLEXPRESS | H70: DHL EXPRESS JANVIER 2025- RAZAFIMAMONJY MIRANA- RMBT 21900 | L70: 19280
A71: 0 | B71: TIERS | C71: 45688 | D71: ="1048" -> 1048 | E71: 45688 | F71: FAC06012025 | G71: FONDHLEXPRESS | H71: DHL EXPRESS JANVIER 2025- CENTRE DE SANTE BE NY SOA- REG FAC06012025 | L71: 185600
A72: 0 | B72: TIERS | C72: 45688 | D72: ="1048" -> 1048 | E72: 45688 | F72: 0125/001 | G72: FONDHLEXPRESS | H72: DHL EXPRESS JANVIER 2025- CENTRE MEDICAL COLISEUM- REG 0125/001 | L72: 124800
A73: 0 | B73: TIERS | C73: 45688 | D73: ="1048" -> 1048 | E73: 45688 | F73: 24/7589 | G73: FONDHLEXPRESS | H73: DHL EXPRESS JANVIER 2025- CLINIQUE NOA- REG 24/7589 | L73: 2045513
A74: 0 | B74: TIERS | C74: 45688 | D74: ="1048" -> 1048 | E74: 45688 | F74: FAC07012025 | G74: FONDHLEXPRESS | H74: DHL EXPRESS JANVIER 2025- EYE CARE (OPHTALMO)- REG FAC07012025 | L74: 739360
A75: 0 | B75: TIERS | C75: 45688 | D75: ="1048" -> 1048 | E75: 45688 | F75: MDR/OP/77263 | G75: FONDHLEXPRESS | H75: DHL EXPRESS JANVIER 2025- CENTRE DE SANTE DR AGARWAL'S - REG MDR/OP/7 | L75: 160000
A76: 0 | B76: TIERS | C76: 45688 | D76: ="1048" -> 1048 | E76: 45688 | F76: FAC24-50603 | G76: FONDHLEXPRESS | H76: DHL EXPRESS JANVIER 2025- IMAGERIE INSTITUT MEDICAL DE MADAG- REG FAC | L76: 674800
A77: 0 | B77: TIERS | C77: 45688 | D77: ="1048" -> 1048 | E77: 45688 | F77: AA24-01784/F | G77: FONDHLEXPRESS | H77: DHL EXPRESS JANVIER 2025- INSTITUT PASTEUR DE MADAGASCAR- REG AA24-01 | L77: 1169460
A78: 0 | B78: TIERS | C78: 45688 | D78: ="1048" -> 1048 | E78: 45688 | F78: FAC06112024 | G78: FONDHLEXPRESS | H78: DHL EXPRESS JANVIER 2025- MATERNITE DU CENTRE REFERENCE MEDICAL- REG | L78: 40000
A79: 0 | B79: TIERS | C79: 45688 | D79: ="1048" -> 1048 | E79: 45688 | F79: FACT/027270 | G79: FONDHLEXPRESS | H79: DHL EXPRESS JANVIER 2025- ORL AUDIOLOGY CLINIC AMBOHIBAO- REG FACT/02 | L79: 32000
A80: 0 | B80: TIERS | C80: 45688 | D80: ="1048" -> 1048 | E80: 45688 | F80: ="2836" -> 2836 | G80: FONDHLEXPRESS | H80: DHL EXPRESS JANVIER 2025- PHARMACIE COLISEUM- REG 2836 | L80: 102320
A81: 0 | B81: TIERS | C81: 45688 | D81: ="1048" -> 1048 | E81: 45688 | F81: FAC/030766/2024 | G81: FONDHLEXPRESS | H81: DHL EXPRESS JANVIER 2025- PHARMACIE CROIX DU SUD- REG FAC/030766/2024 | L81: 37040
A82: 0 | B82: TIERS | C82: 45688 | D82: ="1048" -> 1048 | E82: 45688 | F82: 112870/PH/AV/2024 | G82: FONDHLEXPRESS | H82: DHL EXPRESS JANVIER 2025- PHARMACIE D'AVARADRANO- REG 112870/PH/AV/20 | L82: 181520
A83: 0 | B83: TIERS | C83: 45688 | D83: ="1048" -> 1048 | E83: 45688 | F83: ="001778" -> 001778 | G83: FONDHLEXPRESS | H83: DHL EXPRESS JANVIER 2025- PHARMACIE D'IVATO- REG 001778 | L83: 164720
A84: 0 | B84: TIERS | C84: 45688 | D84: ="1048" -> 1048 | E84: 45688 | F84: VP-1079347 | G84: FONDHLEXPRESS | H84: DHL EXPRESS JANVIER 2025- PHARMACIE GRACE- REG VP-1079347 | L84: 406080
A85: 0 | B85: TIERS | C85: 45688 | D85: ="1048" -> 1048 | E85: 45688 | F85: LOT5877/279510 | G85: FONDHLEXPRESS | H85: DHL EXPRESS JANVIER 2025- PHARMACIE MANDROSOA- REG LOT5877/279510 | L85: 64800
A86: 0 | B86: TIERS | C86: 45688 | D86: ="1048" -> 1048 | E86: 45688 | F86: LOT24931/363268 | G86: FONDHLEXPRESS | H86: DHL EXPRESS JANVIER 2025- PHARMACIE PRINCIPALE- REG LOT24931/363268 | L86: 202080
A87: 0 | B87: TIERS | C87: 45688 | D87: ="1048" -> 1048 | E87: 45688 | F87: 000020/24Y | G87: FONDHLEXPRESS | H87: DHL EXPRESS JANVIER 2025- PHARMACIE TOKY- REG 000020/24Y | L87: 18560
A88: 0 | B88: TIERS | C88: 45688 | D88: ="1048" -> 1048 | E88: 45688 | F88: FAC14062024 | G88: FONDHLEXPRESS | H88: DHL EXPRESS JANVIER 2025- SAINT JOSEPH MEDICAL SERVICES- REG FAC14062 | L88: 16000
A89: 0 | B89: TIERS | C89: 45688 | D89: ="1048" -> 1048 | E89: 45688 | F89: 12/24/095 | G89: FONDHLEXPRESS | H89: DHL EXPRESS JANVIER 2025- VEL'OPTIC- REG 12/24/095 | L89: 1000000
A90: 0 | B90: TIERS | C90: 45688 | D90: ="1048" -> 1048 | E90: 45688 | F90: 004/JANVIER/VV/20 | G90: FONDHLEXPRESS | H90: DHL EXPRESS JANVIER 2025- VEL'VISION (OPHTALMO)- REG 004/JANVIER/VV/2 | L90: 96000
A91: 0 | B91: TIERS | C91: 45695 | D91: ="1651" -> 1651 | E91: 45695 | F91: ="22073" -> 22073 | G91: FONDHLEXPRESS | H91: DHL EXPRESS FEVRIER 2025- RAKOTONANAHARY EDMOND HERVÃ‰- RMBT 22073 | L91: 162018
A92: 0 | B92: TIERS | C92: 45689 | D92: ="1653" -> 1653 | E92: 45689 | F92: ="22024" -> 22024 | G92: FONDHLEXPRESS | H92: DHL EXPRESS FEVRIER 2025- RAKOTONANAHARY EDMOND HERVÃ‰- RMBT 22024 | L92: 1825000
A93: 0 | B93: TIERS | C93: 45709 | D93: ="2042" -> 2042 | E93: 45709 | F93: ="22374" -> 22374 | G93: FONDHLEXPRESS | H93: DHL EXPRESS FEVRIER 2025- RASAMOELINIAINA LINDA FAMENONTSOA- RMBT 223 | L93: 535240
A94: 0 | B94: MVOMCI | C94: 45716 | D94: ="2077" -> 2077 | E94: 45716 | F94: ="22374" -> 22374 | G94: FONDHLEXPRESS | H94: Frais DHL EXPRESS FEVRIER 2025- RASAMOELINIAINA LINDA FAMENONTSOA- RM | L94: 2500
A95: 0 | B95: BOADHL | C95: 45716 | D95: ="2094" -> 2094 | E95: 45716 | G95: FONDHLEXPRESS | H95: Frais de Tenue de Compte Mois de FEVRIER 2025 | L95: 10800
A96: 0 | B96: BOADHL | C96: 45716 | D96: ="2095" -> 2095 | E96: 45716 | G96: FONDHLEXPRESS | H96: Commission de Mouvements Mois de FEVRIER 2025 | L96: 78959.28
A97: 0 | B97: BOADHL | C97: 45698 | D97: ="2097" -> 2097 | E97: 45698 | G97: FONDHLEXPRESS | H97: FRAIS DHL DC 211224 311224 | L97: 3000
A98: 0 | B98: BOADHL | C98: 45698 | D98: ="2099" -> 2099 | E98: 45698 | G98: FONDHLEXPRESS | H98: Frais DHL EXPRESS JANVIER 2025- RAZAFIMAMONJY MIRANA- RMBT 21900 | L98: 9600
A99: 0 | B99: BOADHL | C99: 45706 | D99: ="2100" -> 2100 | E99: 45706 | G99: FONDHLEXPRESS | H99: FRAIS DHL DC 310125 | L99: 3000
A100: 0 | B100: BOADHL | C100: 45709 | D100: ="2101" -> 2101 | E100: 45709 | G100: FONDHLEXPRESS | H100: Frais DHL EXPRESS FEVRIER 2025- RAKOTONANAHARY EDMOND HERVÃ‰- RMBT 22 | L100: 9600
...
